custom_scripts/atmplot.py
custom_scripts/diagnostics.py
custom_scripts/optimize.py
custom_scripts/response.py
custom_scripts/rv_torque.py
custom_scripts/sens_plot.py
custom_scripts/sensitivity_analysis.py
custom_scripts/sensitivity_annotation_plots.py
custom_scripts/maneuverability/angle_vel.py
custom_scripts/maneuverability/boundary_layer_reynolds.py
custom_scripts/maneuverability/cl_pert.py
custom_scripts/maneuverability/init_pos.py
custom_scripts/maneuverability/init_vel.py
custom_scripts/maneuverability/mack.py
custom_scripts/maneuverability/maneuverability.py
custom_scripts/maneuverability/pitch.py
include/atmosphere.h
include/gravity.h
include/guidance.h
include/maneuverability.h
include/physics.h
include/sensors.h
include/trajectory.h
include/utils.h
include/vehicle.h
include/optimize/brent.h
include/optimize/mnbrak.h
include/optimize/nrutil.c
include/optimize/nrutil.h
include/rng/rng.h
include/rng/mt19937-64/mt19937-64.c
include/rng/mt19937-64/mt19937-64test.c
include/rng/mt19937-64/mt64.h
pytrajlib/__init__.py
pytrajlib/_traj.abi3.so
pytrajlib/build.py
pytrajlib/plot.py
pytrajlib/simulation.py
pytrajlib/utils.py
pytrajlib/config/atmprofiles.txt
pytrajlib/config/default.toml
pytrajlib/config/mean_atm.txt
pytrajlib-1.0.0a6.dist-info/METADATA
pytrajlib-1.0.0a6.dist-info/WHEEL
pytrajlib-1.0.0a6.dist-info/entry_points.txt
pytrajlib-1.0.0a6.dist-info/top_level.txt
pytrajlib-1.0.0a6.dist-info/RECORD
pytrajlib-1.0.0a6.dist-info/licenses/LICENSE
