Metadata-Version: 2.4
Name: pytrajlib
Version: 1.0.0a6
Summary: Simulate the flight of a ballistic missile
Author: L.M. Arthur, A.M. Decker
Requires-Python: >=3.10
License-File: LICENSE
Requires-Dist: matplotlib>=3.10.1
Requires-Dist: numpy>=2.2.4
Requires-Dist: pandas>=2.2.3
Requires-Dist: scipy>=1.15.2
Requires-Dist: cffi>=1.17.1
Requires-Dist: folium>=0.20.0
Requires-Dist: tqdm>=4.67.1
Requires-Dist: scienceplots>=2.1.1
Dynamic: license-file
